dphelper/__init__.py
dphelper/config.py
dphelper/helper.py
dphelper/schemas.py
dphelper/connection/__init__.py
dphelper/connection/fetch.py
dphelper/snapshot/__init__.py
dphelper/snapshot/snapshot.py
dphelper-0.0.21.dist-info/METADATA
dphelper-0.0.21.dist-info/WHEEL
dphelper-0.0.21.dist-info/licenses/license
dphelper-0.0.21.dist-info/RECORD
