Metadata-Version: 2.1
Name: dphelper
Version: 0.0.21
Summary: Handle common scraping problems, help linking data platform entities
Author-email: Egidijus Gylys <EgidijusGylys1@gmail.com>, Vilius Visockas <vilius.visockas@gmail.com>, Žygimantas Remeika <Zygimantas.Remeika@gmail.com>
License-File: license
Classifier: Operating System :: OS Independent
Classifier: Programming Language :: Python :: 3
Requires-Python: >=3.7
Requires-Dist: fake-headers
Requires-Dist: pydantic<3.0.0,>1.0.0
Requires-Dist: requests
